annel/__init__.py
annel/adaline_lab3.py
annel/cnn_lab5.py
annel/filters_lab6.py
annel/mlp_lab4.py
annel/perceptron_lab2.py
annel/torch_basics_lab1.py
annel-1.0.1.dist-info/licenses/LICENSE
annel-1.0.1.dist-info/METADATA
annel-1.0.1.dist-info/WHEEL
annel-1.0.1.dist-info/top_level.txt
annel-1.0.1.dist-info/RECORD
